icd10_c2cdc/__init__.py
icd10_c2cdc/recode.py
icd10_c2cdc-0.0.2.dist-info/LICENSE
icd10_c2cdc-0.0.2.dist-info/METADATA
icd10_c2cdc-0.0.2.dist-info/WHEEL
icd10_c2cdc-0.0.2.dist-info/top_level.txt
icd10_c2cdc-0.0.2.dist-info/RECORD
