Metadata-Version: 2.1
Name: icd10-c2cdc
Version: 0.0.2
Summary: Converts ICD-10 codes to CDC/NCHS Selected Causes of Death codes.
Home-page: https://github.com/gadkeidar/recode
Author: Gad Keidar
Author-email: gadkeidar@gmail.com
License: Mozilla Public License Version 2.0
Keywords: ICD-10,CDC,NCHS,death,mortality,recode
Platform: UNKNOWN
Classifier: Development Status :: 5 - Production/Stable
Classifier: Intended Audience :: Healthcare Industry
Classifier: License :: OSI Approved :: MIT License
Classifier: Operating System :: OS Independent
Classifier: Programming Language :: Python :: 3
Classifier: Programming Language :: Python :: 3.8
Classifier: Topic :: Text Processing :: General
Requires-Dist: anytree
